LICENSE
MANIFEST.in
PKG-INFO
babel.cfg
pylintrc
run_tests.sh
setup.cfg
setup.py
tox.ini
vsm.spec
bin/auto_key_gen
bin/check_xtrust_crudini
bin/exp_ceph-common_upgrade
bin/exp_ceph-mds_upgrade
bin/exp_ceph_upgrade
bin/get_smart_info
bin/import_ceph_conf
bin/intergrate-cluster
bin/key
bin/kill_diamond
bin/nvme
bin/presentpool
bin/rbd_ls
bin/refresh-cluster-status
bin/refresh-osd-status
bin/spot_info_list
bin/start_osd
bin/vsm-agent
bin/vsm-all
bin/vsm-api
bin/vsm-assist
bin/vsm-backup
bin/vsm-ceph-upgrade
bin/vsm-conductor
bin/vsm-manage
bin/vsm-physical
bin/vsm-reporter
bin/vsm-restore
bin/vsm-rootwrap
bin/vsm-scheduler
contrib/redhat-eventlet.patch
dist/vsm-2013.1.1-py2.7.egg
doc/.gitignore
doc/Makefile
doc/VSM High Level Design.pdf
doc/find_autodoc_modules.sh
doc/generate_autodoc_index.sh
doc/ext/__init__.py
doc/ext/cinder_autodoc.py
doc/ext/cinder_todo.py
doc/source/conf.py
doc/source/index.rst
doc/source/_ga/layout.html
doc/source/_static/.gitignore
doc/source/_static/.placeholder
doc/source/_static/basic.css
doc/source/_static/default.css
doc/source/_static/jquery.tweet.js
doc/source/_static/tweaks.css
doc/source/_templates/.gitignore
doc/source/_templates/.placeholder
doc/source/_theme/layout.html
doc/source/_theme/theme.conf
doc/source/devref/addmethod.openstackapi.rst
doc/source/devref/api.rst
doc/source/devref/architecture.rst
doc/source/devref/auth.rst
doc/source/devref/cinder.rst
doc/source/devref/database.rst
doc/source/devref/development.environment.rst
doc/source/devref/fakes.rst
doc/source/devref/gerrit.rst
doc/source/devref/il8n.rst
doc/source/devref/index.rst
doc/source/devref/jenkins.rst
doc/source/devref/launchpad.rst
doc/source/devref/rpc.rst
doc/source/devref/scheduler.rst
doc/source/devref/services.rst
doc/source/devref/threading.rst
doc/source/devref/unit_tests.rst
doc/source/devref/volume.rst
doc/source/images/rpc/arch.png
doc/source/images/rpc/arch.svg
doc/source/images/rpc/flow1.png
doc/source/images/rpc/flow1.svg
vsm.egg-info/PKG-INFO
vsm.egg-info/SOURCES.txt
vsm.egg-info/dependency_links.txt
vsm.egg-info/entry_points.txt
vsm.egg-info/requires.txt
vsm.egg-info/top_level.txt
